agents_redis/__init__.py
agents_redis/context.py
agents_redis/integration.py
agents_redis/session.py
openai_agents_redis-0.2.0rc1.dist-info/METADATA
openai_agents_redis-0.2.0rc1.dist-info/WHEEL
openai_agents_redis-0.2.0rc1.dist-info/licenses/LICENSE
openai_agents_redis-0.2.0rc1.dist-info/RECORD
