Metadata-Version: 2.4
Name: openai-agents-redis
Version: 0.2.0rc1
Summary: Session management for OpenAI Agents SDK using Redis.
Project-URL: Homepage, https://github.com/rafaelpierre/openai-agents-redis
Project-URL: Repository, https://github.com/rafaelpierre/openai-agents-redis
Author: Rafael Pierre
License: MIT
License-File: LICENSE
Classifier: License :: OSI Approved :: MIT License
Classifier: Operating System :: OS Independent
Classifier: Programming Language :: Python :: 3
Requires-Python: >=3.13
Requires-Dist: openai-agents>=0.2.2
Requires-Dist: redis[hiredis]>=6.2.0
